vcologen.py
vcologen-1.1.2.dist-info/LICENSE
vcologen-1.1.2.dist-info/METADATA
vcologen-1.1.2.dist-info/WHEEL
vcologen-1.1.2.dist-info/top_level.txt
vcologen-1.1.2.dist-info/RECORD
