Metadata-Version: 2.1
Name: vcologen
Version: 1.1.2
Summary: vim colorscheme generator
Home-page: https://github.com/laddge/vcologen
Author: Laddge
Author-email: dev.laddge@gmail.com
License: MIT
Platform: UNKNOWN
License-File: LICENSE
Requires-Dist: jinja2
